crspy_lite_code/__init__.py
crspy_lite_code/data.py
crspy_lite_code/full_process_wrapper.py
crspy_lite_code/processing_functions.py
crspy_lite_code/visualisation_functions.py
crspy_lite-0.2.1.dist-info/METADATA
crspy_lite-0.2.1.dist-info/WHEEL
crspy_lite-0.2.1.dist-info/entry_points.txt
crspy_lite-0.2.1.dist-info/top_level.txt
crspy_lite-0.2.1.dist-info/RECORD
