Metadata-Version: 2.4
Name: crspy_lite
Version: 0.2.1
Summary: A single site Cosmic-Ray Neutron Sensing (CRNS) processing tool for soil moisture estimation.
Home-page: https://github.com/Joe-Wagstaff/crspy-lite
Author: Joe Wagstaff
Author-email: joe.d.wagstaff@gmail.com
Classifier: Programming Language :: Python :: 3
Classifier: License :: OSI Approved :: MIT License
Classifier: Operating System :: OS Independent
Requires-Python: >=3.7
Requires-Dist: pandas
Requires-Dist: numpy
Requires-Dist: matplotlib
Requires-Dist: bokeh
Requires-Dist: beautifulsoup4
Requires-Dist: lxml
Requires-Dist: scipy
Dynamic: author
Dynamic: author-email
Dynamic: classifier
Dynamic: description
Dynamic: description-content-type
Dynamic: home-page
Dynamic: requires-dist
Dynamic: requires-python
Dynamic: summary
